questmind/__init__.py
questmind/cli.py
questmind/pdf_processor.py
questmind/api/__init__.py
questmind/api/models.py
questmind/api/tool_calling.py
questmind/api/utils.py
questmind/cache/__init__.py
questmind/cache/paged_cache.py
questmind/cache/prefix_cache.py
questmind/cache/vlm_cache.py
questmind/engine/__init__.py
questmind/engine/base.py
questmind/engine/batched.py
questmind/engine/request.py
questmind/engine/simple.py
questmind/inference/__init__.py
questmind/inference/generate.py
questmind/inference/prompt_utils.py
questmind/inference/sample_utils.py
questmind/inference/tokenizer_utils.py
questmind/inference/utils.py
questmind/models/__init__.py
questmind/models/base.py
questmind/models/cache.py
questmind/models/llm.py
questmind/models/mllm.py
questmind/models/qwen3_vl/__init__.py
questmind/models/qwen3_vl/config.py
questmind/models/qwen3_vl/language.py
questmind/models/qwen3_vl/qwen3_vl.py
questmind/models/qwen3_vl/vision.py
questmind/models/qwen3_vl_moe/__init__.py
questmind/models/qwen3_vl_moe/config.py
questmind/models/qwen3_vl_moe/language.py
questmind/models/qwen3_vl_moe/qwen3_vl_moe.py
questmind/models/qwen3_vl_moe/vision.py
questmind/scheduler/__init__.py
questmind/scheduler/engine_core.py
questmind/scheduler/model_registry.py
questmind/scheduler/output_collector.py
questmind/scheduler/scheduler.py
questmind/server/__init__.py
questmind/server/app.py
questmind/utils/__init__.py
questmind/utils/chat_templates.py
questmind/utils/mamba_cache.py
questmind/utils/tokenizer.py
questmind-0.3.6.dist-info/licenses/LICENSE
questmind-0.3.6.dist-info/METADATA
questmind-0.3.6.dist-info/WHEEL
questmind-0.3.6.dist-info/entry_points.txt
questmind-0.3.6.dist-info/top_level.txt
questmind-0.3.6.dist-info/RECORD
