Metadata-Version: 2.4
Name: questmind
Version: 0.3.6
Summary: Local VLM server and document processor for Apple Silicon
Author-email: Luis Miguel Barrera Arbelaez <support@questmind.app>
License: Proprietary
Project-URL: Homepage, https://github.com/lubauss/questmind
Project-URL: Repository, https://github.com/lubauss/questmind
Project-URL: Issues, https://github.com/lubauss/questmind/issues
Keywords: vlm,llm,mlx,apple-silicon,pdf,rag,vision,qwen
Classifier: Development Status :: 4 - Beta
Classifier: Intended Audience :: Developers
Classifier: License :: Other/Proprietary License
Classifier: Operating System :: MacOS
Classifier: Programming Language :: Python :: 3
Classifier: Programming Language :: Python :: 3.10
Classifier: Programming Language :: Python :: 3.11
Classifier: Programming Language :: Python :: 3.12
Classifier: Topic :: Scientific/Engineering :: Artificial Intelligence
Requires-Python: >=3.10
License-File: LICENSE
Requires-Dist: mlx>=0.20.0
Requires-Dist: mlx-lm>=0.20.0
Requires-Dist: pillow>=10.0.0
Requires-Dist: torchvision>=0.18.0
Requires-Dist: transformers<=5.0.0rc1,>=4.45.0
Requires-Dist: tokenizers>=0.19.0
Requires-Dist: huggingface-hub>=0.23.0
Requires-Dist: fastapi>=0.100.0
Requires-Dist: uvicorn>=0.23.0
Requires-Dist: pydantic>=2.0.0
Requires-Dist: python-multipart>=0.0.6
Requires-Dist: PyMuPDF>=1.23.0
Requires-Dist: sentence-transformers>=3.0.0
Requires-Dist: rank_bm25>=0.2.2
Requires-Dist: numpy>=1.24.0
Requires-Dist: tqdm>=4.65.0
Provides-Extra: full
Requires-Dist: jsonschema>=4.0.0; extra == "full"
Provides-Extra: dev
Requires-Dist: pytest>=7.0.0; extra == "dev"
Requires-Dist: black>=23.0.0; extra == "dev"
Requires-Dist: ruff>=0.1.0; extra == "dev"
Dynamic: license-file
